{
  "dog_key": "каро--уиппет",
  "records": [
    {
      "id": 1848,
      "breed": "Уиппет",
      "sex": "К",
      "name": "Каро",
      "speed_km_h": 63,
      "date": "2025-12-03",
      "screenshot_url": "https://disk.yandex.ru/i/fFO8hgLGKo8kfg",
      "status": "normal",
      "updated_at": "2026-06-30 11:38:42",
      "history": [
        {
          "speed_km_h": 62,
          "date": "2025-11-23"
        }
      ]
    },
    {
      "id": 1971,
      "breed": "Уиппет",
      "sex": "К",
      "name": "Каро",
      "speed_km_h": 62,
      "date": "2025-11-23",
      "screenshot_url": "https://disk.yandex.ru/i/HGNLy4zF-FQIuw",
      "status": "old",
      "updated_at": "2026-06-30 11:38:42",
      "history": [
        {
          "speed_km_h": 63,
          "date": "2025-12-03"
        }
      ]
    }
  ]
}