{"id":"ипатова|н|в","name":"ИПАТОВА НАДЕЖДА ВЛАДИМИРОВНА","total_judged":11,"unique_breeds":42,"by_year":{"2025":11},"breeds":[{"breed":"НЕМЕЦКИЙ ШПИЦ ТОЙ (ПОМЕРАНСКИЙ) БЕЛЫЙ, ЧЁРНЫЙ, КОРИЧНЕВЫЙ, ОРАНЖЕВЫЙ, СЕРЫЙ И ДРУГИЕ ОКРАСЫ","count":39},{"breed":"ВЕЛЬШ КОРГИ ПЕМБРОК","count":31},{"breed":"ЙОРКШИРСКИЙ ТЕРЬЕР","count":19},{"breed":"МОПС","count":19},{"breed":"ЛАБРАДОР РЕТРИВЕР","count":17},{"breed":"СИБА","count":16},{"breed":"ДЖЕК РАССЕЛ ТЕРЬЕР","count":15},{"breed":"СТАФФОРДШИРСКИЙ ТЕРЬЕР","count":13},{"breed":"НЬЮФАУНДЛЕНД","count":12},{"breed":"СРЕДНЕАЗИАТСКАЯ ОВЧАРКА","count":12},{"breed":"БИГЛЬ","count":11},{"breed":"ЧИХУАХУА ДЛИННОШЕРСТНАЯ","count":10},{"breed":"ШЕЛТИ","count":10},{"breed":"АМЕРИКАНСКИЙ КОКЕР СПАНИЕЛЬ","count":9},{"breed":"ФРАНЦУЗСКИЙ БУЛЬДОГ","count":9},{"breed":"СИБИРСКИЙ ХАСКИ","count":7},{"breed":"ВЕЛЬШ КОРГИ","count":6},{"breed":"ФРАНЦУЗСКИЙ КОРОТКОШЕРСТНАЯ","count":6},{"breed":"АМЕРИКАНСКАЯ АКИТА","count":5},{"breed":"БЕРНСКИЙ ЗЕННЕНХУНД","count":5},{"breed":"ВЕСТ ХАЙЛЕНД УАЙТ ТЕРЬЕР","count":5},{"breed":"КОНТИНЕНТАЛЬНЫЙТОЙ СПАНИЕЛЬ (ПАПИЙОН - ФАЛЕН)","count":5},{"breed":"САМОЕД","count":4},{"breed":"ВОЛЬФШПИЦ (КЕЕСХОНД)","count":3},{"breed":"МАЛЫЙ ШПИЦ ОРАНЖЕВЫЙ, СЕРЫЙ И ДРУГИЕ ОКРАСЫ","count":3},{"breed":"ФРАНЦУЗСКИЙ ДЛИННОШЕРСТНАЯ","count":3},{"breed":"ЧАУ ЧАУ","count":3},{"breed":"*БИГЛЬ","count":1},{"breed":"*СИБА","count":1},{"breed":"АКИТА АМЕРИКАНСКАЯ","count":1},{"breed":"ВЕСТ ХАЙЛЕНД","count":1},{"breed":"ДШИРСК","count":1},{"breed":"ЛЕОНБЕРГЕР НЕМЕЦКИЙ","count":1},{"breed":"НЕМЕЦКИЙ БОКСЁР","count":1},{"breed":"НЕМЕЦКИЙ ШПИЦ","count":1},{"breed":"РИЗЕНШНАУЦЕР ЧЁРНЫЙ","count":1},{"breed":"СЕТТЕР АМЕРИКАНСКИЙ","count":1},{"breed":"СТАФФОР","count":1},{"breed":"ХАЙЛЕНД","count":1},{"breed":"ЦВЕРГПИНЧЕР","count":1},{"breed":"ЧИХУАХУА ДЛИННОШЕРСТНАЯ ШИ ТЦУ","count":1},{"breed":"ЧИХУАХУА КОРОТКОШЕРСТНАЯ","count":1}],"exhibitions":[{"id":80851,"date":"27.07.2025","title":"Выставка клуба КРОО \"КПЦ КИРОВ\"","rkf_url":"https://rkf.online/exhibitions/80851","grade_counts":{"excellent":10,"very_promising":5},"breed_counts":{"МАЛЫЙ ШПИЦ ОРАНЖЕВЫЙ, СЕРЫЙ И ДРУГИЕ ОКРАСЫ":1,"НЕМЕЦКИЙ ШПИЦ ТОЙ (ПОМЕРАНСКИЙ) БЕЛЫЙ, ЧЁРНЫЙ, КОРИЧНЕВЫЙ, ОРАНЖЕВЫЙ, СЕРЫЙ И ДРУГИЕ ОКРАСЫ":7,"МОПС":6,"ЧИХУАХУА ДЛИННОШЕРСТНАЯ":1}},{"id":79928,"date":"23.11.2025","title":"Выставка клуба УРОО \"ФАУНА+\"","rkf_url":"https://rkf.online/exhibitions/79928","grade_counts":{"very_good":10,"excellent":13},"breed_counts":{"ВЕЛЬШ КОРГИ ПЕМБРОК":23}},{"id":79929,"date":"23.11.2025","title":"Выставка клуба УРОО \"ФАУНА+\"","rkf_url":"https://rkf.online/exhibitions/79929","grade_counts":{"excellent":6,"very_promising":1,"very_good":6},"breed_counts":{"ЙОРКШИРСКИЙ ТЕРЬЕР":3,"НЕМЕЦКИЙ ШПИЦ ТОЙ (ПОМЕРАНСКИЙ) БЕЛЫЙ, ЧЁРНЫЙ, КОРИЧНЕВЫЙ, ОРАНЖЕВЫЙ, СЕРЫЙ И ДРУГИЕ ОКРАСЫ":6,"ЧИХУАХУА ДЛИННОШЕРСТНАЯ":4}},{"id":79086,"date":"22.02.2025","title":"Выставка клуба РОО СОЮЗ КИНОЛОГОВ ВЯТКИ","rkf_url":"https://rkf.online/exhibitions/79086","grade_counts":{"very_promising":2,"excellent":1},"breed_counts":{"ДШИРСК":1,"СТАФФОР":1,"ХАЙЛЕНД":1}},{"id":80212,"date":"19.04.2025","title":"Выставка клуба РРОО КОР \"АТЛАНТИДА ДОГ\"","rkf_url":"https://rkf.online/exhibitions/80212","grade_counts":{"excellent":4},"breed_counts":{"НЕМЕЦКИЙ ШПИЦ ТОЙ (ПОМЕРАНСКИЙ) БЕЛЫЙ, ЧЁРНЫЙ, КОРИЧНЕВЫЙ, ОРАНЖЕВЫЙ, СЕРЫЙ И ДРУГИЕ ОКРАСЫ":3,"КОНТИНЕНТАЛЬНЫЙТОЙ СПАНИЕЛЬ (ПАПИЙОН - ФАЛЕН)":1}},{"id":77911,"date":"18.01.2025","title":"Рейтинговая выставка (ранга ЧРКФ с особым статусом) клуба ТООЛЖ","rkf_url":"https://rkf.online/exhibitions/77911","grade_counts":{"excellent":47,"very_promising":5,"promising":1},"breed_counts":{"БЕРНСКИЙ ЗЕННЕНХУНД":5,"НЕМЕЦКИЙ БОКСЁР":1,"РИЗЕНШНАУЦЕР ЧЁРНЫЙ":1,"ВОЛЬФШПИЦ (КЕЕСХОНД)":3,"НЕМЕЦКИЙ ШПИЦ":1,"МАЛЫЙ ШПИЦ ОРАНЖЕВЫЙ, СЕРЫЙ И ДРУГИЕ ОКРАСЫ":2,"НЕМЕЦКИЙ ШПИЦ ТОЙ (ПОМЕРАНСКИЙ) БЕЛЫЙ, ЧЁРНЫЙ, КОРИЧНЕВЫЙ, ОРАНЖЕВЫЙ, СЕРЫЙ И ДРУГИЕ ОКРАСЫ":11,"СИБА":12,"АМЕРИКАНСКИЙ КОКЕР СПАНИЕЛЬ":9,"МОПС":11}},{"id":78759,"date":"18.01.2025","title":"Выставка клуба ТООЛЖ","rkf_url":"https://rkf.online/exhibitions/78759","grade_counts":{"excellent":80,"very_promising":14,"very_good":2},"breed_counts":{"ВЕЛЬШ КОРГИ ПЕМБРОК":8,"ШЕЛТИ":5,"НЬЮФАУНДЛЕНД":10,"СРЕДНЕАЗИАТСКАЯ ОВЧАРКА":7,"СТАФФОРДШИРСКИЙ ТЕРЬЕР":5,"ВЕСТ ХАЙЛЕНД УАЙТ ТЕРЬЕР":3,"ДЖЕК РАССЕЛ ТЕРЬЕР":3,"ЙОРКШИРСКИЙ ТЕРЬЕР":4,"АМЕРИКАНСКАЯ АКИТА":5,"САМОЕД":4,"СИБИРСКИЙ ХАСКИ":7,"БИГЛЬ":7,"ЛАБРАДОР РЕТРИВЕР":14,"КОНТИНЕНТАЛЬНЫЙТОЙ СПАНИЕЛЬ (ПАПИЙОН - ФАЛЕН)":4,"ФРАНЦУЗСКИЙ БУЛЬДОГ":5,"ЧИХУАХУА КОРОТКОШЕРСТНАЯ":1,"ЧИХУАХУА ДЛИННОШЕРСТНАЯ":5,"ЧИХУАХУА ДЛИННОШЕРСТНАЯ ШИ ТЦУ":1}},{"id":81284,"date":"13.04.2025","title":"Выставка клуба РОО БЭСТ-КЛУБ","rkf_url":"https://rkf.online/exhibitions/81284","grade_counts":{"excellent":44,"very_promising":6,"very_good":5},"breed_counts":{"ВЕЛЬШ КОРГИ":6,"ШЕЛТИ":3,"ЛЕОНБЕРГЕР НЕМЕЦКИЙ":1,"НЬЮФАУНДЛЕНД":2,"СРЕДНЕАЗИАТСКАЯ ОВЧАРКА":1,"СТАФФОРДШИРСКИЙ ТЕРЬЕР":8,"ВЕСТ ХАЙЛЕНД":1,"ДЖЕК РАССЕЛ ТЕРЬЕР":2,"ЙОРКШИРСКИЙ ТЕРЬЕР":4,"АКИТА АМЕРИКАНСКАЯ":1,"НЕМЕЦКИЙ ШПИЦ ТОЙ (ПОМЕРАНСКИЙ) БЕЛЫЙ, ЧЁРНЫЙ, КОРИЧНЕВЫЙ, ОРАНЖЕВЫЙ, СЕРЫЙ И ДРУГИЕ ОКРАСЫ":7,"СИБА":4,"СЕТТЕР АМЕРИКАНСКИЙ":1,"ЛАБРАДОР РЕТРИВЕР":3,"МОПС":1,"ФРАНЦУЗСКИЙ БУЛЬДОГ":1,"ФРАНЦУЗСКИЙ КОРОТКОШЕРСТНАЯ":6,"ФРАНЦУЗСКИЙ ДЛИННОШЕРСТНАЯ":3}},{"id":77895,"date":"09.03.2025","title":"Рейтинговая выставка (ранга ЧРКФ с особым статусом) клуба ООМРКЛСК \"ЗООЦЕНТР\"","rkf_url":"https://rkf.online/exhibitions/77895","grade_counts":{"excellent":16,"very_good":1},"breed_counts":{"ВЕСТ ХАЙЛЕНД УАЙТ ТЕРЬЕР":2,"ДЖЕК РАССЕЛ ТЕРЬЕР":8,"ЙОРКШИРСКИЙ ТЕРЬЕР":7}},{"id":78386,"date":"08.02.2025","title":"Выставка клуба РОО КС \"МАКНАЛИС\"","rkf_url":"https://rkf.online/exhibitions/78386","grade_counts":{"excellent":4},"breed_counts":{"ШЕЛТИ":2,"*СИБА":1,"*БИГЛЬ":1}},{"id":80351,"date":"01.02.2025","title":"Выставка клуба МКОО \"СК-Ю\"","rkf_url":"https://rkf.online/exhibitions/80351","grade_counts":{"excellent":16,"very_promising":4,"very_good":4},"breed_counts":{"СРЕДНЕАЗИАТСКАЯ ОВЧАРКА":4,"ЦВЕРГПИНЧЕР":1,"ДЖЕК РАССЕЛ ТЕРЬЕР":2,"ЙОРКШИРСКИЙ ТЕРЬЕР":1,"НЕМЕЦКИЙ ШПИЦ ТОЙ (ПОМЕРАНСКИЙ) БЕЛЫЙ, ЧЁРНЫЙ, КОРИЧНЕВЫЙ, ОРАНЖЕВЫЙ, СЕРЫЙ И ДРУГИЕ ОКРАСЫ":5,"ЧАУ ЧАУ":3,"БИГЛЬ":4,"МОПС":1,"ФРАНЦУЗСКИЙ БУЛЬДОГ":3}}],"strictness":{"graded":307,"grades":{"excellent":241,"very_good":28,"good":0,"satisfactory":0,"very_promising":37,"promising":1,"dq":0},"excellent_rate":0.7850162866449512,"below_excellent_rate":0.21498371335504887}}