{"id":"tatiana|r|*","name":"Tatiana RASCHIKHMAROVA","total_judged":2,"unique_breeds":9,"by_year":{"2021":2},"breeds":[{"breed":"СХИППЕРКЕ","count":8},{"breed":"СТАРОАНГЛИЙСКАЯ ОВЧАРКА","count":6},{"breed":"БОРОДАТЫЙ КОЛЛИ","count":5},{"breed":"КАНГАЛЬСКАЯ ОВЧАРКА","count":3},{"breed":"АВСТРАЛИЙСКАЯ ПАСТУШЬЯ СОБАКА","count":2},{"breed":"СЛОВАЦКИЙ ЧУВАЧ","count":2},{"breed":"ВОЛЧЬЯ СОБАКА СААРЛОСА","count":1},{"breed":"МУДИ","count":1},{"breed":"ПУМИ","count":1}],"exhibitions":[{"id":61,"date":"13.06.2021","title":"Мемориал А.П. Мазовера 2020» (CACIB FCI)","rkf_url":"https://lc.rkfshow.ru/RKF/ExhibitionResults/ExhibitionResultListView?exhibitionId=61","grade_counts":{"excellent":4},"breed_counts":{"ВОЛЧЬЯ СОБАКА СААРЛОСА":1,"МУДИ":1,"ПУМИ":1,"СЛОВАЦКИЙ ЧУВАЧ":2}},{"id":66,"date":"12.06.2021","title":"Мемориал А.П. Мазовера 2021» (CACIB FCI)","rkf_url":"https://lc.rkfshow.ru/RKF/ExhibitionResults/ExhibitionResultListView?exhibitionId=66","grade_counts":{"excellent":23,"very_good":2,"very_promising":4,"promising":1},"breed_counts":{"АВСТРАЛИЙСКАЯ ПАСТУШЬЯ СОБАКА":2,"БОРОДАТЫЙ КОЛЛИ":5,"СТАРОАНГЛИЙСКАЯ ОВЧАРКА":6,"СХИППЕРКЕ":8,"КАНГАЛЬСКАЯ ОВЧАРКА":3}}],"strictness":{"graded":34,"grades":{"excellent":27,"very_good":2,"good":0,"satisfactory":0,"very_promising":4,"promising":1,"dq":0},"excellent_rate":0.7941176470588235,"below_excellent_rate":0.20588235294117646}}