{
  "schema": "coursing-stats/competition-v1",
  "exported_at": "2026-07-07T17:16:29.219Z",
  "source": "d1-pc-db-local",
  "event_id": 1301,
  "event": {
    "id": 1301,
    "year": 2026,
    "date_start": "2026-04-04",
    "date_end": null,
    "rank_label": "ЧРКФ\n(БЗМП)",
    "event_type": "bzmp",
    "competition_kind": "ЧРКФ",
    "competition_type": "БЗМП",
    "title": "Курсинг Ярославль — ЧРКФ (БЗМП)",
    "host_club": "ОО \"Ярославский Областной Клуб Спортивно-Прикладного Собаководства\"",
    "region": null,
    "location": "Ярославская область, Ярославль",
    "catalog_url": "http://procoursing.ru/2026/2026-04-04_Catalog_BZMP.pdf",
    "results_url": "http://procoursing.ru/2026/2026-04-04_Complete_Results_BZMP.html",
    "confirmed": 1,
    "last_modified": null,
    "scraped_at": "2026-06-27 20:19:37",
    "telegram_url": null,
    "full_title": null,
    "event_date": null,
    "protocol_location": null,
    "judges": "Лукина Д.М., Гродинская Т.Л.",
    "track_schemes": [
      {
        "number": 1,
        "url": "http://procoursing.ru/2026/2026-04-04_M1.png",
        "name": "Схема трассы",
        "length": "700 м"
      },
      {
        "number": 1,
        "url": "http://procoursing.ru/2026/2026-04-04_M2.png",
        "name": "Схема трассы",
        "length": "700 м"
      }
    ]
  },
  "result_count": 8,
  "results": [
    {
      "id": 6316,
      "event_id": 1301,
      "dog_id": 647,
      "breed_class": "Бедлингтон терьер - Стандартный - Кобели",
      "catalog_no": null,
      "placement": 1,
      "total_score": 328,
      "judge_count": 2,
      "qualification": "",
      "vc": "+",
      "status": "finished",
      "raw_scores_json": {
        "heats": [
          {
            "heat_number": 43,
            "bib_number": 43,
            "judges": [
              {
                "judge_number": 1,
                "scores": [
                  17,
                  17,
                  17,
                  17,
                  17
                ],
                "sum": 85
              },
              {
                "judge_number": 2,
                "scores": [
                  15,
                  15,
                  14,
                  16,
                  17
                ],
                "sum": 77
              }
            ],
            "total": 85,
            "disqualified": false,
            "disqualification_reason": null
          },
          {
            "heat_number": 63,
            "bib_number": 63,
            "judges": [
              {
                "judge_number": 1,
                "scores": [
                  17,
                  17,
                  17,
                  15,
                  16
                ],
                "sum": 82
              },
              {
                "judge_number": 2,
                "scores": [
                  17,
                  17,
                  16,
                  16,
                  18
                ],
                "sum": 84
              }
            ],
            "total": 82,
            "disqualified": false,
            "disqualification_reason": null
          }
        ],
        "grand_total": 328,
        "normalized_score": 328,
        "format": "bzmp"
      },
      "raw_text": " <td rowspan=\"2\"><font style=\"font-size:10pt\" face=\"Arial\" color=\"#000000\">1</font></td> <td rowspan=\"2\"><font style=\"font-size:10pt\" face=\"Arial\" color=\"#000000\"><i>1</i></font></td> <td rowspan=\"2\"><font style=\"font-size:10pt\" face=\"Arial\" color=\"#000000\">Бедлингтон терьер</font></td> <td rowspan=\"2\"><font style=\"font-size:10pt\" face=\"Arial\" color=\"#000000\">Стандартный</font></td> <td rowspan=\"2\"><font style=\"font-size:10pt\" face=\"Arial\" color=\"#000000\">Кобель</font></td> <td rowspan=\"2\"><font style=\"font-size:10pt\" face=\"Arial\" color=\"#000000\">MILORD RICHARD  IZ RELAX LANDA</font></td> <td rowspan=\"2\" bgcolor=\"#ff0000\"><font style=\"font-size:10pt\" face=\"Arial\" color=\"#000000\"><i>43</i></font></td> <td><font style=\"font-size:10pt\" face=\"Arial\" color=\"#000000\">17</font></td> <td><font style=\"font-size:10pt\" face=\"Arial\" color=\"#000000\">17</font></td> <td><font style=\"font-size:10pt\" face=\"Arial\" color=\"#000000\">17</font></td> <td><font style=\"font-size:10pt\" face=\"Arial\" color=\"#000000\">17</font></td> <td><font style=\"font-size:10pt\" face=\"Arial\" color=\"#000000\">17</font></td> <td><font style=\"font-size:10pt\" face=\"Arial\" color=\"#000000\"><b>85</b></font></td> <td rowspan=\"2\"><font style=\"font-size:11pt\" face=\"Arial\" color=\"#000000\"><b>162</b></font></td> <td rowspan=\"2\" bgcolor=\"#ff0000\"><font style=\"font-size:10pt\" face=\"Arial\" color=\"#000000\"><i>63</i></font></td> <td><font style=\"font-size:10pt\" face=\"Arial\" color=\"#000000\">17</font></td> <td><font style=\"font-size:10pt\" face=\"Arial\" color=\"#000000\">17</font></td> <td><font style=\"font-size:10pt\" face=\"Arial\" color=\"#000000\">17</font></td> <td><font style=\"font-size:10pt\" face=\"Arial\" color=\"#000000\">15</font></td> <td><font style=\"font-size:10pt\" face=\"Arial\" color=\"#000000\">16</font></td> <td><font style=\"font-size:10pt\" face=\"Arial\" color=\"#000000\"><b>82</b></font></td> <td rowspan=\"2\"><font style=\"font-size:11pt\" face=\"Arial\" color=\"#000000\"><b>166</b></font></td> <td rowspan=\"2\" bgcolor=\"#cd7f32\"><font style=\"font-size:12pt\" face=\"Arial\" color=\"#000000\"><b><abbr title=\"Третий результат состязания\">328</abbr></b></font></td> <td rowspan=\"2\"><font style=\"font-size:10pt\" face=\"Arial\" color=\"#000000\">+</font></td> <td rowspan=\"2\"><font style=\"font-size:10pt\" face=\"Arial\" color=\"#000000\"></font></td> ",
      "judges": "",
      "status_reason": "",
      "dog_key": "milord-richard-iz-relax-landa--бедлингтон-терьер",
      "dog": {
        "id": 647,
        "dog_key": "milord-richard-iz-relax-landa--бедлингтон-терьер",
        "name_lat": "MILORD RICHARD IZ RELAX LANDA",
        "name_ru": "MILORD RICHARD IZ RELAX LANDA",
        "breed": "БЕДЛИНГТОН ТЕРЬЕР",
        "sex": null,
        "owner": null
      }
    },
    {
      "id": 6317,
      "event_id": 1301,
      "dog_id": 648,
      "breed_class": "Бигль - Стандартный - Кобели",
      "catalog_no": null,
      "placement": 1,
      "total_score": 298,
      "judge_count": 2,
      "qualification": "",
      "vc": "",
      "status": "finished",
      "raw_scores_json": {
        "heats": [
          {
            "heat_number": 45,
            "bib_number": 45,
            "judges": [
              {
                "judge_number": 1,
                "scores": [
                  16,
                  17,
                  17,
                  10,
                  15
                ],
                "sum": 75
              },
              {
                "judge_number": 2,
                "scores": [
                  14,
                  14,
                  14,
                  13,
                  14
                ],
                "sum": 69
              }
            ],
            "total": 75,
            "disqualified": false,
            "disqualification_reason": null
          },
          {
            "heat_number": 63,
            "bib_number": 63,
            "judges": [
              {
                "judge_number": 1,
                "scores": [
                  15,
                  17,
                  17,
                  14,
                  16
                ],
                "sum": 79
              },
              {
                "judge_number": 2,
                "scores": [
                  15,
                  15,
                  15,
                  14,
                  16
                ],
                "sum": 75
              }
            ],
            "total": 79,
            "disqualified": false,
            "disqualification_reason": null
          }
        ],
        "grand_total": 298,
        "normalized_score": 298,
        "format": "bzmp"
      },
      "raw_text": " <td rowspan=\"2\"><font style=\"font-size:10pt\" face=\"Arial\" color=\"#000000\">1</font></td> <td rowspan=\"2\"><font style=\"font-size:10pt\" face=\"Arial\" color=\"#000000\"><i>2</i></font></td> <td rowspan=\"2\"><font style=\"font-size:10pt\" face=\"Arial\" color=\"#000000\">Бигль</font></td> <td rowspan=\"2\"><font style=\"font-size:10pt\" face=\"Arial\" color=\"#000000\">Стандартный</font></td> <td rowspan=\"2\"><font style=\"font-size:10pt\" face=\"Arial\" color=\"#000000\">Кобель</font></td> <td rowspan=\"2\"><font style=\"font-size:10pt\" face=\"Arial\" color=\"#000000\">ВЕРСАЧЕ БРАЙТ КРИСТАЛ /<br>VERSACE BRIGHT CRYSTAL</font></td> <td rowspan=\"2\" bgcolor=\"#ff0000\"><font style=\"font-size:10pt\" face=\"Arial\" color=\"#000000\"><i>45</i></font></td> <td><font style=\"font-size:10pt\" face=\"Arial\" color=\"#000000\">16</font></td> <td><font style=\"font-size:10pt\" face=\"Arial\" color=\"#000000\">17</font></td> <td><font style=\"font-size:10pt\" face=\"Arial\" color=\"#000000\">17</font></td> <td><font style=\"font-size:10pt\" face=\"Arial\" color=\"#000000\">10</font></td> <td><font style=\"font-size:10pt\" face=\"Arial\" color=\"#000000\">15</font></td> <td><font style=\"font-size:10pt\" face=\"Arial\" color=\"#000000\"><b>75</b></font></td> <td rowspan=\"2\"><font style=\"font-size:11pt\" face=\"Arial\" color=\"#000000\"><b>144</b></font></td> <td rowspan=\"2\" bgcolor=\"#f0ffff\"><font style=\"font-size:10pt\" face=\"Arial\" color=\"#000000\"><i>63</i></font></td> <td><font style=\"font-size:10pt\" face=\"Arial\" color=\"#000000\">15</font></td> <td><font style=\"font-size:10pt\" face=\"Arial\" color=\"#000000\">17</font></td> <td><font style=\"font-size:10pt\" face=\"Arial\" color=\"#000000\">17</font></td> <td><font style=\"font-size:10pt\" face=\"Arial\" color=\"#000000\">14</font></td> <td><font style=\"font-size:10pt\" face=\"Arial\" color=\"#000000\">16</font></td> <td><font style=\"font-size:10pt\" face=\"Arial\" color=\"#000000\"><b>79</b></font></td> <td rowspan=\"2\"><font style=\"font-size:11pt\" face=\"Arial\" color=\"#000000\"><b>154</b></font></td> <td rowspan=\"2\"><font style=\"font-size:12pt\" face=\"Arial\" color=\"#000000\"><b>298</b></font></td> <td rowspan=\"2\"><font style=\"font-size:10pt\" face=\"Arial\" color=\"#000000\"></font></td> <td rowspan=\"2\"><font style=\"font-size:10pt\" face=\"Arial\" color=\"#000000\"></font></td> ",
      "judges": "",
      "status_reason": "",
      "dog_key": "версаче-браит-кристал-versace-bright-cry--бигль",
      "dog": {
        "id": 648,
        "dog_key": "версаче-браит-кристал-versace-bright-cry--бигль",
        "name_lat": "ВЕРСАЧЕ БРАЙТ КРИСТАЛ /VERSACE BRIGHT CRYSTAL",
        "name_ru": "ВЕРСАЧЕ БРАЙТ КРИСТАЛ /VERSACE BRIGHT CRYSTAL",
        "breed": "БИГЛЬ",
        "sex": null,
        "owner": null
      }
    },
    {
      "id": 6318,
      "event_id": 1301,
      "dog_id": 649,
      "breed_class": "Бигль - Стандартный - Кобели",
      "catalog_no": null,
      "placement": 1,
      "total_score": 328,
      "judge_count": 2,
      "qualification": "Чемпион РКФ, RegCACMB",
      "vc": "+",
      "status": "finished",
      "raw_scores_json": {
        "heats": [
          {
            "heat_number": 42,
            "bib_number": 42,
            "judges": [
              {
                "judge_number": 1,
                "scores": [
                  17,
                  17,
                  17,
                  16,
                  17
                ],
                "sum": 84
              },
              {
                "judge_number": 2,
                "scores": [
                  15,
                  16,
                  16,
                  17,
                  17
                ],
                "sum": 81
              }
            ],
            "total": 84,
            "disqualified": false,
            "disqualification_reason": null
          },
          {
            "heat_number": 64,
            "bib_number": 64,
            "judges": [
              {
                "judge_number": 1,
                "scores": [
                  17,
                  17,
                  17,
                  15,
                  17
                ],
                "sum": 83
              },
              {
                "judge_number": 2,
                "scores": [
                  16,
                  16,
                  16,
                  15,
                  17
                ],
                "sum": 80
              }
            ],
            "total": 83,
            "disqualified": false,
            "disqualification_reason": null
          }
        ],
        "grand_total": 328,
        "normalized_score": 328,
        "format": "bzmp"
      },
      "raw_text": " <td rowspan=\"2\"><font style=\"font-size:10pt\" face=\"Arial\" color=\"#000000\">1</font></td> <td rowspan=\"2\"><font style=\"font-size:10pt\" face=\"Arial\" color=\"#000000\"><i>5</i></font></td> <td rowspan=\"2\"><font style=\"font-size:10pt\" face=\"Arial\" color=\"#000000\">Бультерьер миниатюрный</font></td> <td rowspan=\"2\"><font style=\"font-size:10pt\" face=\"Arial\" color=\"#000000\">Стандартный</font></td> <td rowspan=\"2\"><font style=\"font-size:10pt\" face=\"Arial\" color=\"#000000\">Сука</font></td> <td rowspan=\"2\"><font style=\"font-size:10pt\" face=\"Arial\" color=\"#000000\">КУРАЖ КЛАБ ГОДДЕСС /<br>COURAGE CLUB GODDESS</font></td> <td rowspan=\"2\" bgcolor=\"#f0ffff\"><font style=\"font-size:10pt\" face=\"Arial\" color=\"#000000\"><i>42</i></font></td> <td><font style=\"font-size:10pt\" face=\"Arial\" color=\"#000000\">17</font></td> <td><font style=\"font-size:10pt\" face=\"Arial\" color=\"#000000\">17</font></td> <td><font style=\"font-size:10pt\" face=\"Arial\" color=\"#000000\">17</font></td> <td><font style=\"font-size:10pt\" face=\"Arial\" color=\"#000000\">16</font></td> <td><font style=\"font-size:10pt\" face=\"Arial\" color=\"#000000\">17</font></td> <td><font style=\"font-size:10pt\" face=\"Arial\" color=\"#000000\"><b>84</b></font></td> <td rowspan=\"2\"><font style=\"font-size:11pt\" face=\"Arial\" color=\"#000000\"><b>165</b></font></td> <td rowspan=\"2\" bgcolor=\"#ff0000\"><font style=\"font-size:10pt\" face=\"Arial\" color=\"#000000\"><i>64</i></font></td> <td><font style=\"font-size:10pt\" face=\"Arial\" color=\"#000000\">17</font></td> <td><font style=\"font-size:10pt\" face=\"Arial\" color=\"#000000\">17</font></td> <td><font style=\"font-size:10pt\" face=\"Arial\" color=\"#000000\">17</font></td> <td><font style=\"font-size:10pt\" face=\"Arial\" color=\"#000000\">15</font></td> <td><font style=\"font-size:10pt\" face=\"Arial\" color=\"#000000\">17</font></td> <td><font style=\"font-size:10pt\" face=\"Arial\" color=\"#000000\"><b>83</b></font></td> <td rowspan=\"2\"><font style=\"font-size:11pt\" face=\"Arial\" color=\"#000000\"><b>163</b></font></td> <td rowspan=\"2\"><font style=\"font-size:12pt\" face=\"Arial\" color=\"#000000\"><b>328</b></font></td> <td rowspan=\"2\"><font style=\"font-size:10pt\" face=\"Arial\" color=\"#000000\">+</font></td> <td rowspan=\"2\"><font style=\"font-size:10pt\" face=\"Arial\" color=\"#000000\">Чемпион РКФ, RegCACMB</font></td> ",
      "judges": "",
      "status_reason": "",
      "dog_key": "кураж-клаб-годдесс-courage-club-goddess--бультерьер-миниатюрныи",
      "dog": {
        "id": 649,
        "dog_key": "кураж-клаб-годдесс-courage-club-goddess--бультерьер-миниатюрныи",
        "name_lat": "КУРАЖ КЛАБ ГОДДЕСС /COURAGE CLUB GODDESS",
        "name_ru": "КУРАЖ КЛАБ ГОДДЕСС /COURAGE CLUB GODDESS",
        "breed": "БУЛЬТЕРЬЕР МИНИАТЮРНЫЙ",
        "sex": null,
        "owner": null
      }
    },
    {
      "id": 6321,
      "event_id": 1301,
      "dog_id": 652,
      "breed_class": "Джек Рассел Терьер - Стандартный - Суки",
      "catalog_no": null,
      "placement": 1,
      "total_score": 331,
      "judge_count": 2,
      "qualification": "",
      "vc": "+",
      "status": "finished",
      "raw_scores_json": {
        "heats": [
          {
            "heat_number": 46,
            "bib_number": 46,
            "judges": [
              {
                "judge_number": 1,
                "scores": [
                  16,
                  18,
                  17,
                  17,
                  19
                ],
                "sum": 87
              },
              {
                "judge_number": 2,
                "scores": [
                  15,
                  15,
                  14,
                  17,
                  17
                ],
                "sum": 78
              }
            ],
            "total": 87,
            "disqualified": false,
            "disqualification_reason": null
          },
          {
            "heat_number": 65,
            "bib_number": 65,
            "judges": [
              {
                "judge_number": 1,
                "scores": [
                  17,
                  17,
                  16,
                  17,
                  18
                ],
                "sum": 85
              },
              {
                "judge_number": 2,
                "scores": [
                  16,
                  16,
                  15,
                  17,
                  17
                ],
                "sum": 81
              }
            ],
            "total": 85,
            "disqualified": false,
            "disqualification_reason": null
          }
        ],
        "grand_total": 331,
        "normalized_score": 331,
        "format": "bzmp"
      },
      "raw_text": " <td rowspan=\"2\"><font style=\"font-size:10pt\" face=\"Arial\" color=\"#000000\">1</font></td> <td rowspan=\"2\"><font style=\"font-size:10pt\" face=\"Arial\" color=\"#000000\"><i>6</i></font></td> <td rowspan=\"2\"><font style=\"font-size:10pt\" face=\"Arial\" color=\"#000000\">Джек Рассел Терьер</font></td> <td rowspan=\"2\"><font style=\"font-size:10pt\" face=\"Arial\" color=\"#000000\">Стандартный</font></td> <td rowspan=\"2\"><font style=\"font-size:10pt\" face=\"Arial\" color=\"#000000\">Сука</font></td> <td rowspan=\"2\"><font style=\"font-size:10pt\" face=\"Arial\" color=\"#000000\">БРЭНА /<br>BRENA</font></td> <td rowspan=\"2\" bgcolor=\"#ff0000\"><font style=\"font-size:10pt\" face=\"Arial\" color=\"#000000\"><i>46</i></font></td> <td><font style=\"font-size:10pt\" face=\"Arial\" color=\"#000000\">16</font></td> <td><font style=\"font-size:10pt\" face=\"Arial\" color=\"#000000\">18</font></td> <td><font style=\"font-size:10pt\" face=\"Arial\" color=\"#000000\">17</font></td> <td><font style=\"font-size:10pt\" face=\"Arial\" color=\"#000000\">17</font></td> <td><font style=\"font-size:10pt\" face=\"Arial\" color=\"#000000\">19</font></td> <td><font style=\"font-size:10pt\" face=\"Arial\" color=\"#000000\"><b>87</b></font></td> <td rowspan=\"2\"><font style=\"font-size:11pt\" face=\"Arial\" color=\"#000000\"><b>165</b></font></td> <td rowspan=\"2\" bgcolor=\"#ff0000\"><font style=\"font-size:10pt\" face=\"Arial\" color=\"#000000\"><i>65</i></font></td> <td><font style=\"font-size:10pt\" face=\"Arial\" color=\"#000000\">17</font></td> <td><font style=\"font-size:10pt\" face=\"Arial\" color=\"#000000\">17</font></td> <td><font style=\"font-size:10pt\" face=\"Arial\" color=\"#000000\">16</font></td> <td><font style=\"font-size:10pt\" face=\"Arial\" color=\"#000000\">17</font></td> <td><font style=\"font-size:10pt\" face=\"Arial\" color=\"#000000\">18</font></td> <td><font style=\"font-size:10pt\" face=\"Arial\" color=\"#000000\"><b>85</b></font></td> <td rowspan=\"2\"><font style=\"font-size:11pt\" face=\"Arial\" color=\"#000000\"><b>166</b></font></td> <td rowspan=\"2\" bgcolor=\"#c0c0c0\"><font style=\"font-size:12pt\" face=\"Arial\" color=\"#000000\"><b><abbr title=\"Второй результат состязания\">331</abbr></b></font></td> <td rowspan=\"2\"><font style=\"font-size:10pt\" face=\"Arial\" color=\"#000000\">+</font></td> <td rowspan=\"2\"><font style=\"font-size:10pt\" face=\"Arial\" color=\"#000000\"></font></td> ",
      "judges": "",
      "status_reason": "",
      "dog_key": "брэна-brena--джек-рассел-терьер",
      "dog": {
        "id": 652,
        "dog_key": "брэна-brena--джек-рассел-терьер",
        "name_lat": "БРЭНА /BRENA",
        "name_ru": "БРЭНА /BRENA",
        "breed": "ДЖЕК РАССЕЛ ТЕРЬЕР",
        "sex": null,
        "owner": null
      }
    },
    {
      "id": 6322,
      "event_id": 1301,
      "dog_id": 653,
      "breed_class": "Самоед - Стандартный - Суки",
      "catalog_no": null,
      "placement": 1,
      "total_score": 336,
      "judge_count": 2,
      "qualification": "",
      "vc": "+",
      "status": "finished",
      "raw_scores_json": {
        "heats": [
          {
            "heat_number": 47,
            "bib_number": 47,
            "judges": [
              {
                "judge_number": 1,
                "scores": [
                  17,
                  17,
                  17,
                  18,
                  18
                ],
                "sum": 87
              },
              {
                "judge_number": 2,
                "scores": [
                  16,
                  16,
                  16,
                  17,
                  17
                ],
                "sum": 82
              }
            ],
            "total": 87,
            "disqualified": false,
            "disqualification_reason": null
          },
          {
            "heat_number": 66,
            "bib_number": 66,
            "judges": [
              {
                "judge_number": 1,
                "scores": [
                  17,
                  17,
                  16,
                  17,
                  18
                ],
                "sum": 85
              },
              {
                "judge_number": 2,
                "scores": [
                  16,
                  16,
                  16,
                  17,
                  17
                ],
                "sum": 82
              }
            ],
            "total": 85,
            "disqualified": false,
            "disqualification_reason": null
          }
        ],
        "grand_total": 336,
        "normalized_score": 336,
        "format": "bzmp"
      },
      "raw_text": " <td rowspan=\"2\"><font style=\"font-size:10pt\" face=\"Arial\" color=\"#000000\">1</font></td> <td rowspan=\"2\"><font style=\"font-size:10pt\" face=\"Arial\" color=\"#000000\"><i>7</i></font></td> <td rowspan=\"2\"><font style=\"font-size:10pt\" face=\"Arial\" color=\"#000000\">Самоед</font></td> <td rowspan=\"2\"><font style=\"font-size:10pt\" face=\"Arial\" color=\"#000000\">Стандартный</font></td> <td rowspan=\"2\"><font style=\"font-size:10pt\" face=\"Arial\" color=\"#000000\">Сука</font></td> <td rowspan=\"2\"><font style=\"font-size:10pt\" face=\"Arial\" color=\"#000000\">СНЕЖНОЕ ОЧАРОВАНИЕ ЖАСМИН ПРИНЦЕСС /<br>SNEZHNOE OCHAROVANIE ZHASMIN PRINCZESS</font></td> <td rowspan=\"2\" bgcolor=\"#ff0000\"><font style=\"font-size:10pt\" face=\"Arial\" color=\"#000000\"><i>47</i></font></td> <td><font style=\"font-size:10pt\" face=\"Arial\" color=\"#000000\">17</font></td> <td><font style=\"font-size:10pt\" face=\"Arial\" color=\"#000000\">17</font></td> <td><font style=\"font-size:10pt\" face=\"Arial\" color=\"#000000\">17</font></td> <td><font style=\"font-size:10pt\" face=\"Arial\" color=\"#000000\">18</font></td> <td><font style=\"font-size:10pt\" face=\"Arial\" color=\"#000000\">18</font></td> <td><font style=\"font-size:10pt\" face=\"Arial\" color=\"#000000\"><b>87</b></font></td> <td rowspan=\"2\"><font style=\"font-size:11pt\" face=\"Arial\" color=\"#000000\"><b>169</b></font></td> <td rowspan=\"2\" bgcolor=\"#ff0000\"><font style=\"font-size:10pt\" face=\"Arial\" color=\"#000000\"><i>66</i></font></td> <td><font style=\"font-size:10pt\" face=\"Arial\" color=\"#000000\">17</font></td> <td><font style=\"font-size:10pt\" face=\"Arial\" color=\"#000000\">17</font></td> <td><font style=\"font-size:10pt\" face=\"Arial\" color=\"#000000\">16</font></td> <td><font style=\"font-size:10pt\" face=\"Arial\" color=\"#000000\">17</font></td> <td><font style=\"font-size:10pt\" face=\"Arial\" color=\"#000000\">18</font></td> <td><font style=\"font-size:10pt\" face=\"Arial\" color=\"#000000\"><b>85</b></font></td> <td rowspan=\"2\"><font style=\"font-size:11pt\" face=\"Arial\" color=\"#000000\"><b>167</b></font></td> <td rowspan=\"2\" bgcolor=\"#ffd700\"><font style=\"font-size:12pt\" face=\"Arial\" color=\"#000000\"><b><abbr title=\"Лучший результат состязания\">336</abbr></b></font></td> <td rowspan=\"2\"><font style=\"font-size:10pt\" face=\"Arial\" color=\"#000000\">+</font></td> <td rowspan=\"2\"><font style=\"font-size:10pt\" face=\"Arial\" color=\"#000000\"></font></td> ",
      "judges": "",
      "status_reason": "",
      "dog_key": "снежное-очарование-жасмин-принцесс-snezh--самоед",
      "dog": {
        "id": 653,
        "dog_key": "снежное-очарование-жасмин-принцесс-snezh--самоед",
        "name_lat": "СНЕЖНОЕ ОЧАРОВАНИЕ ЖАСМИН ПРИНЦЕСС /SNEZHNOE OCHAROVANIE ZHASMIN PRINCZESS",
        "name_ru": "СНЕЖНОЕ ОЧАРОВАНИЕ ЖАСМИН ПРИНЦЕСС /SNEZHNOE OCHAROVANIE ZHASMIN PRINCZESS",
        "breed": "САМОЕД",
        "sex": null,
        "owner": null
      }
    },
    {
      "id": 6323,
      "event_id": 1301,
      "dog_id": 654,
      "breed_class": "Цвергпинчер - Стандартный - Кобели",
      "catalog_no": null,
      "placement": 1,
      "total_score": 324,
      "judge_count": 2,
      "qualification": "",
      "vc": "+",
      "status": "finished",
      "raw_scores_json": {
        "heats": [
          {
            "heat_number": 48,
            "bib_number": 48,
            "judges": [
              {
                "judge_number": 1,
                "scores": [
                  17,
                  17,
                  17,
                  15,
                  16
                ],
                "sum": 82
              },
              {
                "judge_number": 2,
                "scores": [
                  16,
                  16,
                  16,
                  15,
                  16
                ],
                "sum": 79
              }
            ],
            "total": 82,
            "disqualified": false,
            "disqualification_reason": null
          },
          {
            "heat_number": 67,
            "bib_number": 67,
            "judges": [
              {
                "judge_number": 1,
                "scores": [
                  16,
                  17,
                  17,
                  15,
                  17
                ],
                "sum": 82
              },
              {
                "judge_number": 2,
                "scores": [
                  16,
                  17,
                  16,
                  15,
                  17
                ],
                "sum": 81
              }
            ],
            "total": 82,
            "disqualified": false,
            "disqualification_reason": null
          }
        ],
        "grand_total": 324,
        "normalized_score": 324,
        "format": "bzmp"
      },
      "raw_text": " <td rowspan=\"2\"><font style=\"font-size:10pt\" face=\"Arial\" color=\"#000000\">1</font></td> <td rowspan=\"2\"><font style=\"font-size:10pt\" face=\"Arial\" color=\"#000000\"><i>8</i></font></td> <td rowspan=\"2\"><font style=\"font-size:10pt\" face=\"Arial\" color=\"#000000\">Цвергпинчер</font></td> <td rowspan=\"2\"><font style=\"font-size:10pt\" face=\"Arial\" color=\"#000000\">Стандартный</font></td> <td rowspan=\"2\"><font style=\"font-size:10pt\" face=\"Arial\" color=\"#000000\">Кобель</font></td> <td rowspan=\"2\"><font style=\"font-size:10pt\" face=\"Arial\" color=\"#000000\">ЦЕСВИЛЬ ГАРДЕН ИРИНУС ГОЛД БРЕЙН /<br>TSESVIL GARDEN IRINUS GOLD BREIN</font></td> <td rowspan=\"2\" bgcolor=\"#ff0000\"><font style=\"font-size:10pt\" face=\"Arial\" color=\"#000000\"><i>48</i></font></td> <td><font style=\"font-size:10pt\" face=\"Arial\" color=\"#000000\">17</font></td> <td><font style=\"font-size:10pt\" face=\"Arial\" color=\"#000000\">17</font></td> <td><font style=\"font-size:10pt\" face=\"Arial\" color=\"#000000\">17</font></td> <td><font style=\"font-size:10pt\" face=\"Arial\" color=\"#000000\">15</font></td> <td><font style=\"font-size:10pt\" face=\"Arial\" color=\"#000000\">16</font></td> <td><font style=\"font-size:10pt\" face=\"Arial\" color=\"#000000\"><b>82</b></font></td> <td rowspan=\"2\"><font style=\"font-size:11pt\" face=\"Arial\" color=\"#000000\"><b>161</b></font></td> <td rowspan=\"2\" bgcolor=\"#ff0000\"><font style=\"font-size:10pt\" face=\"Arial\" color=\"#000000\"><i>67</i></font></td> <td><font style=\"font-size:10pt\" face=\"Arial\" color=\"#000000\">16</font></td> <td><font style=\"font-size:10pt\" face=\"Arial\" color=\"#000000\">17</font></td> <td><font style=\"font-size:10pt\" face=\"Arial\" color=\"#000000\">17</font></td> <td><font style=\"font-size:10pt\" face=\"Arial\" color=\"#000000\">15</font></td> <td><font style=\"font-size:10pt\" face=\"Arial\" color=\"#000000\">17</font></td> <td><font style=\"font-size:10pt\" face=\"Arial\" color=\"#000000\"><b>82</b></font></td> <td rowspan=\"2\"><font style=\"font-size:11pt\" face=\"Arial\" color=\"#000000\"><b>163</b></font></td> <td rowspan=\"2\"><font style=\"font-size:12pt\" face=\"Arial\" color=\"#000000\"><b>324</b></font></td> <td rowspan=\"2\"><font style=\"font-size:10pt\" face=\"Arial\" color=\"#000000\">+</font></td> <td rowspan=\"2\"><font style=\"font-size:10pt\" face=\"Arial\" color=\"#000000\"></font></td> ",
      "judges": "",
      "status_reason": "",
      "dog_key": "цесвиль-гарден-иринус-голд-бреин-tsesvil--цвергпинчер",
      "dog": {
        "id": 654,
        "dog_key": "цесвиль-гарден-иринус-голд-бреин-tsesvil--цвергпинчер",
        "name_lat": "ЦЕСВИЛЬ ГАРДЕН ИРИНУС ГОЛД БРЕЙН /TSESVIL GARDEN IRINUS GOLD BREIN",
        "name_ru": "ЦЕСВИЛЬ ГАРДЕН ИРИНУС ГОЛД БРЕЙН /TSESVIL GARDEN IRINUS GOLD BREIN",
        "breed": "ЦВЕРГПИНЧЕР",
        "sex": null,
        "owner": null
      }
    },
    {
      "id": 6319,
      "event_id": 1301,
      "dog_id": 650,
      "breed_class": "Бигль - Стандартный - Кобели",
      "catalog_no": null,
      "placement": 2,
      "total_score": 325,
      "judge_count": 2,
      "qualification": "CACMB, RegCACMB",
      "vc": "+",
      "status": "finished",
      "raw_scores_json": {
        "heats": [
          {
            "heat_number": 44,
            "bib_number": 44,
            "judges": [
              {
                "judge_number": 1,
                "scores": [
                  17,
                  17,
                  17,
                  17,
                  17
                ],
                "sum": 85
              },
              {
                "judge_number": 2,
                "scores": [
                  14,
                  14,
                  14,
                  17,
                  16
                ],
                "sum": 75
              }
            ],
            "total": 85,
            "disqualified": false,
            "disqualification_reason": null
          },
          {
            "heat_number": 62,
            "bib_number": 62,
            "judges": [
              {
                "judge_number": 1,
                "scores": [
                  17,
                  17,
                  16,
                  16,
                  17
                ],
                "sum": 83
              },
              {
                "judge_number": 2,
                "scores": [
                  17,
                  17,
                  16,
                  16,
                  16
                ],
                "sum": 82
              }
            ],
            "total": 83,
            "disqualified": false,
            "disqualification_reason": null
          }
        ],
        "grand_total": 325,
        "normalized_score": 325,
        "format": "bzmp"
      },
      "raw_text": " <td rowspan=\"2\"><font style=\"font-size:10pt\" face=\"Arial\" color=\"#000000\">2</font></td> <td rowspan=\"2\"><font style=\"font-size:10pt\" face=\"Arial\" color=\"#000000\"><i>4</i></font></td> <td rowspan=\"2\"><font style=\"font-size:10pt\" face=\"Arial\" color=\"#000000\">Бультерьер миниатюрный</font></td> <td rowspan=\"2\"><font style=\"font-size:10pt\" face=\"Arial\" color=\"#000000\">Стандартный</font></td> <td rowspan=\"2\"><font style=\"font-size:10pt\" face=\"Arial\" color=\"#000000\">Сука</font></td> <td rowspan=\"2\"><font style=\"font-size:10pt\" face=\"Arial\" color=\"#000000\">БАТИДА ДЕ КОКО</font></td> <td rowspan=\"2\" bgcolor=\"#ff0000\"><font style=\"font-size:10pt\" face=\"Arial\" color=\"#000000\"><i>44</i></font></td> <td><font style=\"font-size:10pt\" face=\"Arial\" color=\"#000000\">17</font></td> <td><font style=\"font-size:10pt\" face=\"Arial\" color=\"#000000\">17</font></td> <td><font style=\"font-size:10pt\" face=\"Arial\" color=\"#000000\">17</font></td> <td><font style=\"font-size:10pt\" face=\"Arial\" color=\"#000000\">17</font></td> <td><font style=\"font-size:10pt\" face=\"Arial\" color=\"#000000\">17</font></td> <td><font style=\"font-size:10pt\" face=\"Arial\" color=\"#000000\"><b>85</b></font></td> <td rowspan=\"2\"><font style=\"font-size:11pt\" face=\"Arial\" color=\"#000000\"><b>160</b></font></td> <td rowspan=\"2\" bgcolor=\"#f0ffff\"><font style=\"font-size:10pt\" face=\"Arial\" color=\"#000000\"><i>62</i></font></td> <td><font style=\"font-size:10pt\" face=\"Arial\" color=\"#000000\">17</font></td> <td><font style=\"font-size:10pt\" face=\"Arial\" color=\"#000000\">17</font></td> <td><font style=\"font-size:10pt\" face=\"Arial\" color=\"#000000\">16</font></td> <td><font style=\"font-size:10pt\" face=\"Arial\" color=\"#000000\">16</font></td> <td><font style=\"font-size:10pt\" face=\"Arial\" color=\"#000000\">17</font></td> <td><font style=\"font-size:10pt\" face=\"Arial\" color=\"#000000\"><b>83</b></font></td> <td rowspan=\"2\"><font style=\"font-size:11pt\" face=\"Arial\" color=\"#000000\"><b>165</b></font></td> <td rowspan=\"2\"><font style=\"font-size:12pt\" face=\"Arial\" color=\"#000000\"><b>325</b></font></td> <td rowspan=\"2\"><font style=\"font-size:10pt\" face=\"Arial\" color=\"#000000\">+</font></td> <td rowspan=\"2\"><font style=\"font-size:10pt\" face=\"Arial\" color=\"#000000\">CACMB, RegCACMB</font></td> ",
      "judges": "",
      "status_reason": "",
      "dog_key": "батида-де-коко--бультерьер-миниатюрныи",
      "dog": {
        "id": 650,
        "dog_key": "батида-де-коко--бультерьер-миниатюрныи",
        "name_lat": "БАТИДА ДЕ КОКО",
        "name_ru": "БАТИДА ДЕ КОКО",
        "breed": "БУЛЬТЕРЬЕР МИНИАТЮРНЫЙ",
        "sex": null,
        "owner": null
      }
    },
    {
      "id": 6320,
      "event_id": 1301,
      "dog_id": 651,
      "breed_class": "Бигль - Стандартный - Кобели",
      "catalog_no": null,
      "placement": 3,
      "total_score": 325,
      "judge_count": 2,
      "qualification": "RegCACMB",
      "vc": "+",
      "status": "finished",
      "raw_scores_json": {
        "heats": [
          {
            "heat_number": 42,
            "bib_number": 42,
            "judges": [
              {
                "judge_number": 1,
                "scores": [
                  16,
                  17,
                  17,
                  16,
                  17
                ],
                "sum": 83
              },
              {
                "judge_number": 2,
                "scores": [
                  15,
                  15,
                  15,
                  16,
                  17
                ],
                "sum": 78
              }
            ],
            "total": 83,
            "disqualified": false,
            "disqualification_reason": null
          },
          {
            "heat_number": 62,
            "bib_number": 62,
            "judges": [
              {
                "judge_number": 1,
                "scores": [
                  17,
                  17,
                  16,
                  17,
                  17
                ],
                "sum": 84
              },
              {
                "judge_number": 2,
                "scores": [
                  16,
                  16,
                  16,
                  16,
                  16
                ],
                "sum": 80
              }
            ],
            "total": 84,
            "disqualified": false,
            "disqualification_reason": null
          }
        ],
        "grand_total": 325,
        "normalized_score": 325,
        "format": "bzmp"
      },
      "raw_text": " <td rowspan=\"2\"><font style=\"font-size:10pt\" face=\"Arial\" color=\"#000000\">3</font></td> <td rowspan=\"2\"><font style=\"font-size:10pt\" face=\"Arial\" color=\"#000000\"><i>3</i></font></td> <td rowspan=\"2\"><font style=\"font-size:10pt\" face=\"Arial\" color=\"#000000\">Бультерьер миниатюрный</font></td> <td rowspan=\"2\"><font style=\"font-size:10pt\" face=\"Arial\" color=\"#000000\">Стандартный</font></td> <td rowspan=\"2\"><font style=\"font-size:10pt\" face=\"Arial\" color=\"#000000\">Кобель</font></td> <td rowspan=\"2\"><font style=\"font-size:10pt\" face=\"Arial\" color=\"#000000\">МАРЛЕН-БРАО ЧАРОДЕЙ /<br>MARLEN-BRAO CHARODEI</font></td> <td rowspan=\"2\" bgcolor=\"#ff0000\"><font style=\"font-size:10pt\" face=\"Arial\" color=\"#000000\"><i>42</i></font></td> <td><font style=\"font-size:10pt\" face=\"Arial\" color=\"#000000\">16</font></td> <td><font style=\"font-size:10pt\" face=\"Arial\" color=\"#000000\">17</font></td> <td><font style=\"font-size:10pt\" face=\"Arial\" color=\"#000000\">17</font></td> <td><font style=\"font-size:10pt\" face=\"Arial\" color=\"#000000\">16</font></td> <td><font style=\"font-size:10pt\" face=\"Arial\" color=\"#000000\">17</font></td> <td><font style=\"font-size:10pt\" face=\"Arial\" color=\"#000000\"><b>83</b></font></td> <td rowspan=\"2\"><font style=\"font-size:11pt\" face=\"Arial\" color=\"#000000\"><b>161</b></font></td> <td rowspan=\"2\" bgcolor=\"#ff0000\"><font style=\"font-size:10pt\" face=\"Arial\" color=\"#000000\"><i>62</i></font></td> <td><font style=\"font-size:10pt\" face=\"Arial\" color=\"#000000\">17</font></td> <td><font style=\"font-size:10pt\" face=\"Arial\" color=\"#000000\">17</font></td> <td><font style=\"font-size:10pt\" face=\"Arial\" color=\"#000000\">16</font></td> <td><font style=\"font-size:10pt\" face=\"Arial\" color=\"#000000\">17</font></td> <td><font style=\"font-size:10pt\" face=\"Arial\" color=\"#000000\">17</font></td> <td><font style=\"font-size:10pt\" face=\"Arial\" color=\"#000000\"><b>84</b></font></td> <td rowspan=\"2\"><font style=\"font-size:11pt\" face=\"Arial\" color=\"#000000\"><b>164</b></font></td> <td rowspan=\"2\"><font style=\"font-size:12pt\" face=\"Arial\" color=\"#000000\"><b>325</b></font></td> <td rowspan=\"2\"><font style=\"font-size:10pt\" face=\"Arial\" color=\"#000000\">+</font></td> <td rowspan=\"2\"><font style=\"font-size:10pt\" face=\"Arial\" color=\"#000000\">RegCACMB</font></td> ",
      "judges": "",
      "status_reason": "",
      "dog_key": "марлен-брао-чародеи-marlen-brao-charodei--бультерьер-миниатюрныи",
      "dog": {
        "id": 651,
        "dog_key": "марлен-брао-чародеи-marlen-brao-charodei--бультерьер-миниатюрныи",
        "name_lat": "МАРЛЕН БРАО ЧАРОДЕЙ /MARLEN BRAO CHARODEI",
        "name_ru": "МАРЛЕН БРАО ЧАРОДЕЙ /MARLEN BRAO CHARODEI",
        "breed": "БУЛЬТЕРЬЕР МИНИАТЮРНЫЙ",
        "sex": null,
        "owner": null
      }
    }
  ]
}